emailfinderpy/__init__.py
emailfinderpy/emailfinder.py
emailfinderpy-1.0.1.dist-info/LICENSE
emailfinderpy-1.0.1.dist-info/METADATA
emailfinderpy-1.0.1.dist-info/WHEEL
emailfinderpy-1.0.1.dist-info/top_level.txt
emailfinderpy-1.0.1.dist-info/RECORD
